swarmnode/__init__.py
swarmnode/_client.py
swarmnode/errors.py
swarmnode/pagination.py
swarmnode/types.py
swarmnode/resources/__init__.py
swarmnode/resources/_base.py
swarmnode/resources/agent.py
swarmnode/resources/agent_builder_job.py
swarmnode/resources/agent_executor_cron_jobs.py
swarmnode/resources/agent_executor_job.py
swarmnode/resources/asset.py
swarmnode/resources/build.py
swarmnode/resources/execution.py
swarmnode/resources/store.py
swarmnode-0.4.1.dist-info/LICENSE
swarmnode-0.4.1.dist-info/METADATA
swarmnode-0.4.1.dist-info/WHEEL
swarmnode-0.4.1.dist-info/top_level.txt
swarmnode-0.4.1.dist-info/RECORD
