Metadata-Version: 2.1
Name: swarmnode
Version: 0.4.1
Summary: Deploy serverless AI agents in the cloud. Orchestrate collaboration between agents via the SwarmNode Python SDK.
License: MIT
Classifier: Programming Language :: Python :: 3.8
Classifier: Programming Language :: Python :: 3.9
Classifier: Programming Language :: Python :: 3.10
Classifier: Programming Language :: Python :: 3.11
Classifier: Programming Language :: Python :: 3.12
Requires-Python: >=3.9
License-File: LICENSE
Requires-Dist: requests==2.32.3
Requires-Dist: websockets==13.1
